llama_index/agent/lats/__init__.py
llama_index/agent/lats/step.py
llama_index/agent/lats/types.py
llama_index_agent_lats-0.3.2.dist-info/METADATA
llama_index_agent_lats-0.3.2.dist-info/WHEEL
llama_index_agent_lats-0.3.2.dist-info/licenses/LICENSE
llama_index_agent_lats-0.3.2.dist-info/RECORD
