Metadata-Version: 2.4
Name: llama-index-agent-lats
Version: 0.3.2
Summary: llama-index agent lats integration
Author-email: Your Name <you@example.com>
License-Expression: MIT
License-File: LICENSE
Requires-Python: <4.0,>=3.9
Requires-Dist: llama-index-core<0.13,>=0.12.41
